aesthetic_ascii_mindaug/31-synthwave-sun-waves-electronic-sky.jpg
aesthetic_ascii_mindaug/RobotoMono-VariableFont_wght.ttf
aesthetic_ascii_mindaug/__init__.py
aesthetic_ascii_mindaug/city-5848267_1920.jpg
aesthetic_ascii_mindaug/synthesize.py
aesthetic_ascii_mindaug/wallpaperuse.com-outrun-wallpaper-76590.png
aesthetic_ascii_mindaug/wallpaperuse.com-retro-wallpaper-hd-999925.png
aesthetic_ascii_mindaug/wallpaperuse.com-synthwave-wallpaper-1003075.jpg
aesthetic_ascii_mindaug/wallpaperuse.com-wallpapers-retro-803078.jpg
aesthetic_ascii_mindaug-0.0.4.dist-info/LICENSE
aesthetic_ascii_mindaug-0.0.4.dist-info/METADATA
aesthetic_ascii_mindaug-0.0.4.dist-info/WHEEL
aesthetic_ascii_mindaug-0.0.4.dist-info/top_level.txt
aesthetic_ascii_mindaug-0.0.4.dist-info/RECORD
